Mono_CPU/ALU/alu.v
module ALU(A, B, AluOp, S);
  input [31:0] A, B;
  input [3:0] AluOp;
  output reg [31:0] S;

  always @* begin
    case (AluOp)
      4'b0000: S = A + B;
      4'b1000: S = A - B;
      4'b0001: S = A << B[4:0];
      4'b0010: S = ($signed(A) < $signed(B)) ? 1 : 0;
      4'b0011: S = (A < B) ? 1 : 0;
      4'b0100: S = A ^ B;
      4'b0101: S = A >> B[4:0];
      4'b1101: S = $signed(A) >>> B[4:0];
      4'b0110: S = A | B;
      4'b0111: S = A & B;
      default: S = 4'b0; 
    endcase
  end
endmodule

Mono_CPU/ALU/alu_tb.v
module testbench_my_mux;

  reg [31:0] A, B;
  reg [3:0] AluOp;
  
  wire [31:0] S;

  ALU uut (
    .A(A),
    .B(B),
    .AluOp(AluOp),
    .S(S)
  );

  initial begin
    $dumpfile("dump.vcd");  
    $dumpvars(0, testbench_my_mux);

   // Test case 1: Addition (AluOp = 4'b0000)
    A = 5;
    B = 3;
    AluOp = 4'b0000;
    #10; 
    // Test case 2: Subtraction (AluOp = 4'b1000)
    A = 8;
    B = 3;
    AluOp = 4'b1000;
    #10;
    // Test case 3: Left shift (AluOp = 4'b0001)
    A = 4;
    B = 2;
    AluOp = 4'b0001;
    #10;
    // Test case 4: Signed comparison (AluOp = 4'b0010)
    A = -5;
    B = 3;
    AluOp = 4'b0010;
    #10; 
    // Test case 5: Unsigned comparison (AluOp = 4'b0011)
    A = 5;
    B = 3;
    AluOp = 4'b0011;
    #10; 
    // Test case 6: Bitwise logic (AluOp = 4'b0100)
    A = 5;
    B = 3;
    AluOp = 4'b0100;
    #10; 
    // Test case 7: Right shift (AluOp = 4'b0101)
    A = 8;
    B = 2;
    AluOp = 4'b0101;
    #10;
    // Test case 8: Logical right shift (AluOp = 4'b1101)
    A = -8;
    B = 2;
    AluOp = 4'b1101;
    #10; 
    // Test case 9: Bitwise OR (AluOp = 4'b0110)
    A = 5;
    B = 3;
    AluOp = 4'b0110;
    #10;
    // Test case 10: Bitwise AND (AluOp = 4'b0111)
    A = 5;
    B = 3;
    AluOp = 4'b0111;
    #10; // Wait for 10 time units
    // End of simulation
    $finish;
  end

endmodule

Mono_CPU/ALU/dump.vcd
$date
	Thu Apr 25 19:30:00 2024
$end
$version
	Icarus Verilog
$end
$timescale
	1s
$end
$scope module testbench_my_mux $end
$var wire 32 ! S [31:0] $end
$var reg 32 " A [31:0] $end
$var reg 4 # AluOp [3:0] $end
$var reg 32 $ B [31:0] $end
$scope module uut $end
$var wire 32 % A [31:0] $end
$var wire 4 & AluOp [3:0] $end
$var wire 32 ' B [31:0] $end
$var reg 32 ( S [31:0] $end
$upscope $end
$upscope $end
$enddefinitions $end
$comment Show the parameter values. $end
$dumpall
$end
#0
$dumpvars
b1000 (
b11 '
b0 &
b101 %
b11 $
b0 #
b101 "
b1000 !
$end
#10
b101 !
b101 (
b1000 #
b1000 &
b1000 "
b1000 %
#20
b10000 !
b10000 (
b1 #
b1 &
b10 $
b10 '
b100 "
b100 %
#30
b1 !
b1 (
b10 #
b10 &
b11 $
b11 '
b11111111111111111111111111111011 "
b11111111111111111111111111111011 %
#40
b0 !
b0 (
b11 #
b11 &
b101 "
b101 %
#50
b110 !
b110 (
b100 #
b100 &
#60
b10 !
b10 (
b101 #
b101 &
b10 $
b10 '
b1000 "
b1000 %
#70
b11111111111111111111111111111110 !
b11111111111111111111111111111110 (
b1101 #
b1101 &
b11111111111111111111111111111000 "
b11111111111111111111111111111000 %
#80
b111 !
b111 (
b110 #
b110 &
b11 $
b11 '
b101 "
b101 %
#90
b1 !
b1 (
b111 #
b111 &
