Mono_CPU/Data_Memory/data_memory.v
module data_memory(
    input [31:0] Address,
    input [31:0] DataWr,
    input [2:0] DMCtrl,
    input DMWr,
    output logic [31:0] DataRd
    );
    
     logic [7:0] memory[800:0];

  always @(Address or DataWr or DMCtrl or DMWr) begin
    case (DMCtrl)
      3'b000:  DataRd <= {{24{memory[Address][7]}}, memory[Address]};
      3'b001:  DataRd <= {{16{memory[Address+1][7]}}, memory[Address+1], memory[Address]};
      3'b010:  DataRd <= {memory[Address+3], memory[Address+2], memory[Address+1], memory[Address]};
      3'b100:  DataRd <= {{24{1'b0}}, memory[Address]};
      3'b101:  DataRd <= {{16{1'b0}}, memory[Address+1], memory[Address]};
      default: DataRd <= 0;
    endcase
    if (DMWr)
      #1
      if (DMCtrl == 3'b000) 
        memory[Address] <= DataWr[7:0];
      else if (DMCtrl == 3'b001) begin
        memory[Address]   <= DataWr[7:0];
        memory[Address+1] <= DataWr[15:8];
      end else if (DMCtrl == 3'b010) begin
        memory[Address]   <= DataWr[7:0];
        memory[Address+1] <= DataWr[15:8];
        memory[Address+2] <= DataWr[23:16];
        memory[Address+3] <= DataWr[31:24];
      end
    
  end //always

endmodule

Mono_CPU/Data_Memory/data_memory_tb.v
module data_memory_tb;

logic [31:0] Address;
logic [31:0] DataWr;
logic [2:0] DMCtrl;
logic DMWr;
logic [31:0] DataRd;

data_memory dut(
  .Address(Address),
  .DataWr(DataWr),
  .DMCtrl(DMCtrl),
  .DMWr(DMWr),
  .DataRd(DataRd)
);

  initial begin
    $dumpfile("dump.vcd");
    $dumpvars(0,data_memory_tb);

    //store at address 0 value 8 in byte format
    Address = 0;
    DataWr= 32'h00000008;
    DMCtrl= 3'b000;
    DMWr = 1;
    #10 //0

    //read at address 0 value 8 in unsigned byte format
    Address = 0;
    DataWr= 32'h0000ffff;
    DMCtrl= 3'b100;
    DMWr = 0;
    #10 //80

    //store at address 1 value -2 in half-word format
    Address = 1;
    DataWr= 32'h0000fffe;
    DMCtrl= 3'b001;
    DMWr = 1;
    #10 //10

    //store at address 3 value 2**32 -1 in word format
    Address = 3;
    DataWr= 32'h80000001;
    DMCtrl= 3'b010;
    DMWr = 1;
    #10 //20

    //read at address 10 unknown values
    Address = 10;
    DataWr= 32'h00000008;
    DMCtrl= 3'b000;
    DMWr = 0;
    #10 //30

    //read at address 0 value 8 byte format
    Address = 0;
    DataWr= 32'h00000018;
    DMCtrl= 3'b000;
    DMWr = 0;
    #10 //40
    
    // read at address 1 value -2 in half word format
    Address = 1;
    DataWr= 32'h0fff0ffe;
    DMCtrl= 3'b001;
    DMWr = 0;
    #10 //50

    //read at address 3 value 2**32 -1 in word format
    Address = 3;
    DataWr= 32'h8010f001;
    DMCtrl= 3'b010;
    DMWr = 0;
    #10 //60

    //read at address 1 value fffe in unsigned half-word format
    Address = 1;
    DataWr= 32'h0000ffff;
    DMCtrl= 3'b101;
    DMWr = 0;
    #10 //70

    $finish;

  end
endmodule

Mono_CPU/Data_Memory/dump.vcd
$date
	Tue Apr 23 00:58:47 2024
$end
$version
	Icarus Verilog
$end
$timescale
	1s
$end
$scope module data_memory_tb $end
$var wire 32 ! DataRd [31:0] $end
$var reg 32 " Address [31:0] $end
$var reg 3 # DMCtrl [2:0] $end
$var reg 1 $ DMWr $end
$var reg 32 % DataWr [31:0] $end
$scope module dut $end
$var wire 32 & Address [31:0] $end
$var wire 3 ' DMCtrl [2:0] $end
$var wire 1 $ DMWr $end
$var wire 32 ( DataWr [31:0] $end
$var reg 32 ) DataRd [31:0] $end
$upscope $end
$upscope $end
$enddefinitions $end
$comment Show the parameter values. $end
$dumpall
$end
#0
$dumpvars
b1000 )
b1000 (
b0 '
b0 &
b1000 %
1$
b0 #
b0 "
b1000 !
$end
#10
0$
b100 #
b100 '
b1111111111111111 %
b1111111111111111 (
#20
b11111111111111111111111111111110 !
b11111111111111111111111111111110 )
1$
b1 #
b1 '
b1111111111111110 %
b1111111111111110 (
b1 "
b1 &
#30
b10000000000000000000000000000001 !
b10000000000000000000000000000001 )
b10 #
b10 '
b10000000000000000000000000000001 %
b10000000000000000000000000000001 (
b11 "
b11 &
#40
bx !
bx )
0$
b0 #
b0 '
b1000 %
b1000 (
b1010 "
b1010 &
#50
b1000 !
b1000 )
b11000 %
b11000 (
b0 "
b0 &
#60
b11111111111111111111111111111110 !
b11111111111111111111111111111110 )
b1 #
b1 '
b1111111111110000111111111110 %
b1111111111110000111111111110 (
b1 "
b1 &
#70
b10000000000000000000000000000001 !
b10000000000000000000000000000001 )
b10 #
b10 '
b10000000000100001111000000000001 %
b10000000000100001111000000000001 (
b11 "
b11 &
#80
b1111111111111110 !
b1111111111111110 )
b101 #
b101 '
b1111111111111111 %
b1111111111111111 (
b1 "
b1 &
