Mono_CPU/Branch_Unit/branch_unit.v
module branch_unit (
    input [31:0] rs1,
    input [31:0] rs2,
    input logic [4:0] BrOp,
    output reg NextPCSrc
);

    always @(rs1, rs2, BrOp) begin
        if (BrOp[4] == 1'b1) 
            NextPCSrc <= 1;
        else if (BrOp[4:3] == 2'b00) 
            NextPCSrc <= 0;
        else if (BrOp == 5'b01000)
            NextPCSrc <= (rs1 === rs2);
        else if (BrOp == 5'b01001)
            NextPCSrc <= (rs1 !== rs2);
        else if (BrOp == 5'b01100)
            NextPCSrc <= ($signed(rs1) < $signed(rs2));
        else if (BrOp == 5'b01101)
            NextPCSrc <= ($signed(rs1) >= $signed(rs2));
        else if (BrOp == 5'b01110)
            NextPCSrc <= (rs1 < rs2);
        else if (BrOp == 5'b01111)
            NextPCSrc <= (rs1 >= rs2);
    end// always

endmodule

Mono_CPU/Branch_Unit/branch_unit_tb.v
module branch_unit_tb;

  logic [31:0] rs1;
  logic [31:0] rs2;
  logic [4:0] BrOp;
  logic NextPCSrc;

  branch_unit dut (
    .rs1(rs1),
    .rs2(rs2),
    .BrOp(BrOp),
    .NextPCSrc(NextPCSrc)
  );

  initial begin
    $dumpfile("dump.vcd");  
    $dumpvars(0, branch_unit_tb);
    // Branch always (5'b1xxxx)
    rs1 = 32'h00000001;
    rs2 = 32'h00000001;
    BrOp = 5'b10000;
    #10;
    //Branch never (5'b00xxx)
    rs1 = 32'h00000001;
    rs2 = 32'h00000000;
    BrOp = 5'b00000;
    #10; // Wait for 10 time units
    //Branch equal (5'b01000)
    rs1 = 32'h00000010;
    rs2 = 32'h00000010;
    BrOp = 5'b01000;
    #10;
    //Branch not equal (5'b01001)
    rs1 = 32'h00000001;
    rs2 = 32'h00000001;
    BrOp = 5'b01001;
    #10;
    // Branch less than (signed) (5'b01100)
    rs1 = 32'hf0000003;
    rs2 = 32'h00000002;
    BrOp = 5'b01100;
    #10;
    //Branch greater than or equal to (signed) (5'b01101)
    rs1 = 32'h00000002;
    rs2 = 32'h00000004;
    BrOp = 5'b01101;
    #10; 
    //Branch less than (unsigned) (5'b01110)
    rs1 = 32'h00000001;
    rs2 = 32'h00000002;
    BrOp = 5'b01110;
    #10;
    //Branch greater than or equal to (unsigned) (5'b01111)
    rs1 = 32'h00000002;
    rs2 = 32'h00000001;
    BrOp = 5'b01111;
    #10; 
    $finish;
  end


endmodule

Mono_CPU/Branch_Unit/dump.vcd
$date
	Sun Apr 21 11:23:17 2024
$end
$version
	Icarus Verilog
$end
$timescale
	1s
$end
$scope module branch_unit_tb $end
$var wire 1 ! NextPCSrc $end
$var reg 5 " BrOp [4:0] $end
$var reg 32 # rs1 [31:0] $end
$var reg 32 $ rs2 [31:0] $end
$scope module dut $end
$var wire 5 % BrOp [4:0] $end
$var wire 32 & rs1 [31:0] $end
$var wire 32 ' rs2 [31:0] $end
$var reg 1 ! NextPCSrc $end
$upscope $end
$upscope $end
$enddefinitions $end
$comment Show the parameter values. $end
$dumpall
$end
#0
$dumpvars
b1 '
b1 &
b10000 %
b1 $
b1 #
b10000 "
1!
$end
#10
0!
b0 "
b0 %
b0 $
b0 '
#20
1!
b1000 "
b1000 %
b10000 $
b10000 '
b10000 #
b10000 &
#30
0!
b1001 "
b1001 %
b1 $
b1 '
b1 #
b1 &
#40
1!
b1100 "
b1100 %
b10 $
b10 '
b11110000000000000000000000000011 #
b11110000000000000000000000000011 &
#50
0!
b1101 "
b1101 %
b100 $
b100 '
b10 #
b10 &
#60
1!
b1110 "
b1110 %
b10 $
b10 '
b1 #
b1 &
#70
b1111 "
b1111 %
b1 $
b1 '
b10 #
b10 &
