Mono_CPU/Data_Memory/data_memory.v
module data_memory(
    input [31:0] Address,
    input [31:0] DataWr,
    input [2:0] DMCtrl,
    input DMWr,
    output logic [31:0] DataRd
    );
    
     logic [7:0] memory[800:0];

  always @(Address or DataWr or DMCtrl or DMWr) begin
    case (DMCtrl)
      3'b000:  DataRd <= {{24{memory[Address][7]}}, memory[Address]};
      3'b001:  DataRd <= {{16{memory[Address+1][7]}}, memory[Address+1], memory[Address]};
      3'b010:  DataRd <= {memory[Address+3], memory[Address+2], memory[Address+1], memory[Address]};
      3'b100:  DataRd <= {{24{1'b0}}, memory[Address]};
      3'b101:  DataRd <= {{16{1'b0}}, memory[Address+1], memory[Address]};
      default: DataRd <= 0;
    endcase
    if (DMWr)
      #1
      if (DMCtrl == 3'b000) 
        memory[Address] <= DataWr[7:0];
      else if (DMCtrl == 3'b001) begin
        memory[Address]   <= DataWr[7:0];
        memory[Address+1] <= DataWr[15:8];
      end else if (DMCtrl == 3'b010) begin
        memory[Address]   <= DataWr[7:0];
        memory[Address+1] <= DataWr[15:8];
        memory[Address+2] <= DataWr[23:16];
        memory[Address+3] <= DataWr[31:24];
      end
    
  end //always

endmodule

Mono_CPU/ALU/alu.v
module ALU(A, B, AluOp, S);
  input [31:0] A, B;
  input [3:0] AluOp;
  output reg [31:0] S;

  always @* begin
    case (AluOp)
      4'b0000: S = A + B;
      4'b1000: S = A - B;
      4'b0001: S = A << B[4:0];
      4'b0010: S = ($signed(A) < $signed(B)) ? 1 : 0;
      4'b0011: S = (A < B) ? 1 : 0;
      4'b0100: S = A ^ B;
      4'b0101: S = A >> B[4:0];
      4'b1101: S = $signed(A) >>> B[4:0];
      4'b0110: S = A | B;
      4'b0111: S = A & B;
      default: S = 4'b0; 
    endcase
  end
endmodule

Mono_CPU/Branch_Unit/branch_unit.v
module branch_unit (
    input [31:0] rs1,
    input [31:0] rs2,
    input logic [4:0] BrOp,
    output reg NextPCSrc
);

    always @(rs1, rs2, BrOp) begin
        if (BrOp[4] == 1'b1) 
            NextPCSrc <= 1;
        else if (BrOp[4:3] == 2'b00) 
            NextPCSrc <= 0;
        else if (BrOp == 5'b01000)
            NextPCSrc <= (rs1 === rs2);
        else if (BrOp == 5'b01001)
            NextPCSrc <= (rs1 !== rs2);
        else if (BrOp == 5'b01100)
            NextPCSrc <= ($signed(rs1) < $signed(rs2));
        else if (BrOp == 5'b01101)
            NextPCSrc <= ($signed(rs1) >= $signed(rs2));
        else if (BrOp == 5'b01110)
            NextPCSrc <= (rs1 < rs2);
        else if (BrOp == 5'b01111)
            NextPCSrc <= (rs1 >= rs2);
    end// always

endmodule

Mono_CPU/Registers_Unit/reg_unit.v
module register_unit (
  input wire clk,
  input [4:0] rs1,
  input [4:0] rs2,
  input [4:0] rd,
  input [31:0] DataWr,
  input RUWr,
  output reg [31:0] RURs1,
  output reg [31:0] RURs2
);

  logic [31:0] RU [0:31];

  initial begin
    RU[0] = 32'h00000000;
    RU[1] = 32'h00000001;
    RU[2] = 32'h000000ff;
    RU[3] = 32'h00000003;
    RU[4] = 32'h00000004;
    RU[5] = 32'h00000005;
    RU[6] = 32'h00000006;
    RU[7] = 32'h00000007;
    RU[8] = 32'h00000008;
    RU[9] = 32'h00000009;
    RU[10] = 32'h0000000a;
    RU[11] = 32'h0000000b;
    RU[12] = 32'h0000000c;
  end
  
  assign RURs1 = RU[rs1]; 
  assign RURs2 = RU[rs2];

  always @(posedge clk) begin
    if(RUWr && rd != 0) 
      RU[rd] <= DataWr;
  end //always 
endmodule

Mono_CPU/Imm_Generator/imm_gen.v
module imm_gen (
    input [24:0] imm, 
    input [2:0] ImmSrc, 
    output reg [31:0] ImmExt
    );

    always @* begin
        case(ImmSrc)
            3'b000: ImmExt = {(imm[24] ? 20'hfffff : 20'h00000), imm[24:13]};//I
            3'b001: ImmExt = {(imm[24]? 20'hfffff : 20'h00000), imm[24:18], imm[4:0]}; //S
            3'b101: ImmExt = {(imm[24]? {18'o777777, 1'b1} : {18'o000000, 1'b0}), imm[24], imm[0], imm[23:18], imm[4:1], 1'b0}; //B
            3'b010: ImmExt = {imm[24:5], 12'b0}; //U
            3'b110: ImmExt = {(imm[24]? {8'hff, 3'o7} : {8'h00, 3'o0}), imm[24], imm[12:5], imm[13], imm[23:14], 1'b0};  //J
            default: ImmExt = {20'b0, imm[24:13]};
        endcase
    end

endmodule

Mono_CPU/Unidad_de_Control/control_unit.v
module control_unit(
  input [6:0] OpCode,
  input [2:0] Funct3,
  input [6:0] Funct7,

  output RUWr,
  output AlUASrc,
  output AlUBSrc,
  output DMWr,
  output [1:0]RUDataWrSrc,
  output [2:0]DMCtrl,
  output [2:0]ImmSrc,
  output [3:0]ALUOp,
  output [4:0]BrOp
  
);
  
  assign AlUASrc = OpCode[6] === 1'b1 & OpCode !== 7'b1100111;
  assign AlUBSrc = OpCode !== 8'b0110011;
  assign RUWr = OpCode[5:2] !== 4'b1000;
  assign DMWr = OpCode[6:4] === 3'b010;
  assign RUDataWrSrc = {OpCode[6], ~OpCode[4]} - OpCode[6];
  assign DMCtrl = Funct3;
  assign ALUOp = (OpCode === 7'b0110011 || OpCode === 7'b0010011 ? {(OpCode === 7'b0110011 || Funct3 === 3'b101 ? Funct7[5]: 1'b0 ), Funct3} : 4'b0000);
  assign ImmSrc = {(OpCode === 7'b1101111) | (OpCode === 7'b1100011),(OpCode[2:0] === 3'b111) & (OpCode[4:3] > 3'b00), (OpCode[5:2] === 4'b1000)};
  assign BrOp = {(OpCode[2] & OpCode[6]), OpCode[6],Funct3};

endmodule

Mono_CPU/Instruction_Memory/instruction_memory.v
module instruction_memory(
    input logic [31:0] program_counter,
    output logic [31:0] instruction
    );
    logic [7:0] memory [0:512];
    initial begin
        $readmemh("mul.mem", memory);
    end
    assign instruction = {
        memory[program_counter],
        memory[program_counter+1],
        memory[program_counter+2],
        memory[program_counter+3]};

endmodule

Mono_CPU/PC/program_counter.v
module program_counter(
    input clk, 
    input logic [31:0] pc_input, 
    output logic [31:0] pc_output
    );
    
    always @ (posedge clk)
        pc_output <= pc_input;

endmodule

Mono_CPU/procesador_monociclo.v
`include "PC/program_counter.v"
`include "Instruction_Memory/instruction_memory.v"
`include "Unidad_de_Control/control_unit.v"
`include "Imm_Generator/imm_gen.v"
`include "Registers_Unit/reg_unit.v"
`include "ALU/alu.v"
`include "Data_Memory/data_memory.v"
`include "Branch_Unit/branch_unit.v"

module cpu_mono(
    input clk
);

  //pc signals
  logic [31:0] pc_input_signal;
  logic [31:0] pc_output_signal;

  //instruction memory signals
  logic [31:0] instruction_signal;

  //control unit signals
  logic RUWr_signal, AlUASrc_signal, AlUBSrc_signal, DMWr_signal;
  logic [1:0] RUDataWrSrc_signal;
  logic [2:0] DMCtrl_signal, ImmSrc_signal;
  logic [3:0] ALUOp_signal;
  logic [4:0] BrOp_signal;

  //imm gen signals
  logic [31:0] ImmExt_signal;

  //reg_unit signals
  logic [31:0] RURs1_signal, RURs2_signal, DataWr_signal;

  //branch_unit signals

  //alu signals
  logic [31:0] ALURes;

  //data memory signals
  logic [31:0] DataRd_signal;

  //branch unit signals
  logic NextPCSrc_signal;

  initial begin
    pc_input_signal = 32'h00000000;

    //pc_output_signal = 32'h00000000;
  end

  program_counter pc(
    .clk(clk),
    .pc_input(pc_input_signal), 
    .pc_output(pc_output_signal)
  );

  instruction_memory ins_mem(
    .program_counter(pc_output_signal),
    .instruction(instruction_signal)
  );
  
  control_unit c_u(
    .OpCode(instruction_signal[6:0]),
    .Funct3(instruction_signal[14:12]),
    .Funct7(instruction_signal[31:25]),
    //outputs
    .RUWr(RUWr_signal),
    .AlUASrc(AlUASrc_signal),
    .AlUBSrc(AlUBSrc_signal),
    .DMWr(DMWr_signal),
    .RUDataWrSrc(RUDataWrSrc_signal),
    .DMCtrl(DMCtrl_signal),
    .ImmSrc(ImmSrc_signal),
    .ALUOp(ALUOp_signal),
    .BrOp(BrOp_signal)
  );

  imm_gen imm_gen_module(
    .imm(instruction_signal[31:7]),
    .ImmSrc(ImmSrc_signal),
    .ImmExt(ImmExt_signal)
  );

  register_unit ru(
    .clk(clk),
    .rs1(instruction_signal[19:15]),
    .rs2(instruction_signal[24:20]),
    .rd(instruction_signal[11:7]),
    .DataWr(
      RUDataWrSrc_signal === 2'b00 ? ALURes:
      RUDataWrSrc_signal === 2'b01 ? DataRd_signal:
      pc_output_signal+4
      ),
    .RUWr(RUWr_signal),
    .RURs1(RURs1_signal),
    .RURs2(RURs2_signal)
  );

  branch_unit br_u(
    .rs1(RURs1_signal),
    .rs2(RURs2_signal),
    .BrOp(BrOp_signal),
    .NextPCSrc(NextPCSrc_signal)
  );
  
  ALU alu_unit(
    .A((AlUASrc_signal ? pc_output_signal : RURs1_signal)),
    .B((AlUBSrc_signal ? ImmExt_signal : RURs2_signal)),
    .AluOp(ALUOp_signal),
    .S(ALURes)
  );

  data_memory data_mem(
    .Address(ALURes),
    .DataWr(RURs2_signal),
    .DMCtrl(DMCtrl_signal),
    .DMWr(DMWr_signal),
    .DataRd(DataRd_signal)
  );


  always @(pc_output_signal, NextPCSrc_signal, ALURes) begin
    if(NextPCSrc_signal === 1)
      pc_input_signal <= ALURes;
    else
      pc_input_signal <= pc_output_signal + 4;
  end

endmodule

Mono_CPU/procesador_monociclo_tb.v
module cpu_mono_tb;

  logic clk;

  cpu_mono dut(
      .clk(clk)
  );

  initial begin
    clk = 0;
    forever #5 clk = ~clk;
  end

  initial begin
    $dumpfile("dump.vcd");
    $dumpvars(0,cpu_mono_tb);
    #1340
    $finish;
  end

endmodule

Mono_CPU/dump.vcd
$date
	Fri Apr 26 19:12:33 2024
$end
$version
	Icarus Verilog
$end
$timescale
	1s
$end
$scope module cpu_mono_tb $end
$var reg 1 ! clk $end
$scope module dut $end
$var wire 1 ! clk $end
$var wire 32 " pc_output_signal [31:0] $end
$var wire 32 # instruction_signal [31:0] $end
$var wire 1 $ RUWr_signal $end
$var wire 32 % RURs2_signal [31:0] $end
$var wire 32 & RURs1_signal [31:0] $end
$var wire 2 ' RUDataWrSrc_signal [1:0] $end
$var wire 1 ( NextPCSrc_signal $end
$var wire 3 ) ImmSrc_signal [2:0] $end
$var wire 32 * ImmExt_signal [31:0] $end
$var wire 32 + DataRd_signal [31:0] $end
$var wire 1 , DMWr_signal $end
$var wire 3 - DMCtrl_signal [2:0] $end
$var wire 5 . BrOp_signal [4:0] $end
$var wire 1 / AlUBSrc_signal $end
$var wire 1 0 AlUASrc_signal $end
$var wire 32 1 ALURes [31:0] $end
$var wire 4 2 ALUOp_signal [3:0] $end
$var reg 32 3 pc_input_signal [31:0] $end
$scope module alu_unit $end
$var wire 32 4 A [31:0] $end
$var wire 32 5 B [31:0] $end
$var wire 4 6 AluOp [3:0] $end
$var reg 32 7 S [31:0] $end
$upscope $end
$scope module br_u $end
$var wire 32 8 rs2 [31:0] $end
$var wire 32 9 rs1 [31:0] $end
$var wire 5 : BrOp [4:0] $end
$var reg 1 ( NextPCSrc $end
$upscope $end
$scope module c_u $end
$var wire 1 0 AlUASrc $end
$var wire 3 ; DMCtrl [2:0] $end
$var wire 3 < Funct3 [2:0] $end
$var wire 7 = Funct7 [6:0] $end
$var wire 7 > OpCode [6:0] $end
$var wire 1 $ RUWr $end
$var wire 2 ? RUDataWrSrc [1:0] $end
$var wire 3 @ ImmSrc [2:0] $end
$var wire 1 , DMWr $end
$var wire 5 A BrOp [4:0] $end
$var wire 1 / AlUBSrc $end
$var wire 4 B ALUOp [3:0] $end
$upscope $end
$scope module data_mem $end
$var wire 32 C Address [31:0] $end
$var wire 3 D DMCtrl [2:0] $end
$var wire 1 , DMWr $end
$var wire 32 E DataWr [31:0] $end
$var reg 32 F DataRd [31:0] $end
$upscope $end
$scope module imm_gen_module $end
$var wire 3 G ImmSrc [2:0] $end
$var wire 25 H imm [24:0] $end
$var reg 32 I ImmExt [31:0] $end
$upscope $end
$scope module ins_mem $end
$var wire 32 J program_counter [31:0] $end
$var wire 32 K instruction [31:0] $end
$upscope $end
$scope module pc $end
$var wire 1 ! clk $end
$var wire 32 L pc_input [31:0] $end
$var reg 32 M pc_output [31:0] $end
$upscope $end
$scope module ru $end
$var wire 32 N DataWr [31:0] $end
$var wire 32 O RURs1 [31:0] $end
$var wire 32 P RURs2 [31:0] $end
$var wire 1 $ RUWr $end
$var wire 1 ! clk $end
$var wire 5 Q rd [4:0] $end
$var wire 5 R rs1 [4:0] $end
$var wire 5 S rs2 [4:0] $end
$upscope $end
$upscope $end
$upscope $end
$enddefinitions $end
$comment Show the parameter values. $end
$dumpall
$end
#0
$dumpvars
bx S
bx R
bx Q
bx P
bx O
bx N
bx M
b0 L
bx K
bx J
bx I
bx H
b0 G
bx F
bx E
bx D
bx C
b0 B
bx A
b0 @
bx ?
bx >
bx =
bx <
bx ;
bx :
bx 9
bx 8
bx 7
b0 6
bx 5
bx 4
b0 3
b0 2
bx 1
00
1/
bx .
bx -
0,
bx +
bx *
b0 )
x(
bx '
bx &
bx %
1$
bx #
bx "
0!
$end
#5
0(
b100 3
b100 L
b0 '
b0 ?
b11 1
b11 7
b11 C
b11 5
b0 4
b11 *
b11 I
b11 N
b10011 >
b1010 Q
b0 -
b0 ;
b0 D
b0 .
b0 :
b0 A
b0 <
b0 &
b0 9
b0 O
b0 R
b11 %
b11 8
b11 E
b11 P
b11 S
b110000000001010 H
b0 =
b1100000000010100010011 #
b1100000000010100010011 K
b0 "
b0 J
b0 M
1!
#10
0!
#15
b1000 3
b1000 L
b1011 Q
b110000000001011 H
b1100000000010110010011 #
b1100000000010110010011 K
b100 "
b100 J
b100 M
1!
#20
0!
#25
1(
b10000 3
b10000 L
b1000 4
b10000 1
b10000 7
b10000 C
10
b1100 N
b1000 5
b10 '
b10 ?
b110 )
b110 @
b110 G
b11000 .
b11000 :
b11000 A
b1000 *
b1000 I
b1101111 >
b1 Q
b1000 %
b1000 8
b1000 E
b1000 P
b1000 S
b10000000000000001 H
b100000000000000011101111 #
b100000000000000011101111 K
b1000 "
b1000 J
b1000 M
1!
#30
0!
#35
0(
b10100 3
b10100 L
00
b11111111111111111111111111101100 5
b0 '
b0 ?
b0 )
b0 @
b0 G
b0 .
b0 :
b0 A
b11111111111111111111111111101100 *
b11111111111111111111111111101100 I
b11101011 1
b11101011 7
b11101011 C
b11101011 N
b10011 >
b10 Q
b1100 %
b1100 8
b1100 E
b1100 P
b1100 S
b11111111 &
b11111111 9
b11111111 O
b10 R
b1111111011000001000000010 H
b1111111 =
b11111111 4
b11111110110000010000000100010011 #
b11111110110000010000000100010011 K
b10000 "
b10000 J
b10000 M
1!
#40
0!
#45
b11000 3
b11000 L
b1 '
b1 ?
b0 5
bx N
0$
1,
b1 )
b1 @
b1 G
b0 2
b0 6
b0 B
b0 *
b0 I
b11101011 1
b11101011 7
b11101011 C
b100011 >
b0 Q
b10 -
b10 ;
b10 D
b10 .
b10 :
b10 A
b10 <
b1000 %
b1000 8
b1000 E
b1000 P
b1000 S
b10000001001000000 H
b0 =
b11101011 4
b100000010010000000100011 #
b100000010010000000100011 K
b10100 "
b10100 J
b10100 M
b11101011 &
b11101011 9
b11101011 O
1!
#50
0!
#55
b1000 N
b1000 +
b1000 F
b11100 3
b11100 L
b11101111 1
b11101111 7
b11101111 C
b100 5
b100 *
b100 I
b100 Q
b1001 %
b1001 8
b1001 E
b1001 P
b1001 S
b10010001001000100 H
b100100010010001000100011 #
b100100010010001000100011 K
b11000 "
b11000 J
b11000 M
1!
#60
0!
#65
b1001 N
b1001 +
b1001 F
b100000 3
b100000 L
b11110011 1
b11110011 7
b11110011 C
b1000 5
b1000 *
b1000 I
b1000 Q
bx %
bx 8
bx E
bx P
b10010 S
b100100001001001000 H
b1001000010010010000100011 #
b1001000010010010000100011 K
b11100 "
b11100 J
b11100 M
1!
#70
0!
#75
bx N
bx +
bx F
b100100 3
b100100 L
b11110111 1
b11110111 7
b11110111 C
b1100 5
b1100 *
b1100 I
b1100 Q
b10011 S
b100110001001001100 H
b1001100010010011000100011 #
b1001100010010011000100011 K
b100000 "
b100000 J
b100000 M
1!
#80
0!
#85
b101000 3
b101000 L
b11111011 1
b11111011 7
b11111011 C
b10000 5
b10000 *
b10000 I
b10000 Q
b1100 %
b1100 8
b1100 E
b1100 P
b1 S
b10001001010000 H
b100010010100000100011 #
b100010010100000100011 K
b100100 "
b100100 J
b100100 M
1!
#90
0!
#95
b1100 +
b1100 F
b101100 3
b101100 L
b11 N
b0 '
b0 ?
b11 1
b11 7
b11 C
b0 5
1$
0,
b0 )
b0 @
b0 G
b11 4
b0 *
b0 I
b10011 >
b1000 Q
b0 -
b0 ;
b0 D
b0 .
b0 :
b0 A
b0 <
b0 %
b0 8
b0 E
b0 P
b0 S
b11 &
b11 9
b11 O
b1010 R
b101000001000 H
b1010000010000010011 #
b1010000010000010011 K
b101000 "
b101000 J
b101000 M
1!
#100
0!
#105
b110000 3
b110000 L
b1001 Q
b1011 R
b101100001001 H
b1011000010010010011 #
b1011000010010010011 K
b101100 "
b101100 J
b101100 M
1!
#110
0!
#115
bx +
bx F
b110100 3
b110100 L
b0 N
b0 1
b0 7
b0 C
b0 4
b10010 Q
b0 &
b0 9
b0 O
b0 R
b10010 H
b100100010011 #
b100100010011 K
b110000 "
b110000 J
b110000 M
1!
#120
0!
#125
b111000 3
b111000 L
b1 N
b1 1
b1 7
b1 C
b1 5
b1 *
b1 I
b10011 Q
b1100 %
b1100 8
b1100 E
b1100 P
b1 S
b10000000010011 H
b100000000100110010011 #
b100000000100110010011 K
b110100 "
b110100 J
b110100 M
1!
#130
0!
#135
b0xxxxxxxxxxxxxxxx +
b0xxxxxxxxxxxxxxxx F
b111100 3
b111100 L
b111000 4
10
b111100 N
b1010100 1
b1010100 7
b1010100 C
b11100 5
0$
b10 '
b10 ?
b101 )
b101 @
b101 G
b0 2
b0 6
b0 B
b11100 *
b11100 I
b1100011 >
b11100 Q
b101 -
b101 ;
b101 D
b1101 .
b1101 :
b1101 A
b101 <
b11 %
b11 8
b11 E
b11 P
b1001 S
b10010 R
b10011001010111100 H
b100110010101111001100011 #
b100110010101111001100011 K
b111000 "
b111000 J
b111000 M
1!
#140
0!
#145
bx +
bx F
b1000000 3
b1000000 L
00
b0 5
1$
b0 '
b0 ?
b0 )
b0 @
b0 G
b0 *
b0 I
b1 1
b1 7
b1 C
b1 N
b10011 >
b1010 Q
b1 &
b1 9
b1 O
b10011 R
b0 -
b0 ;
b0 D
b0 .
b0 :
b0 A
b0 <
b0 %
b0 8
b0 E
b0 P
b0 S
b1001100001010 H
b1 4
b10011000010100010011 #
b10011000010100010011 K
b111100 "
b111100 J
b111100 M
1!
#150
0!
#155
b0 +
b0 F
b1000100 3
b1000100 L
b11 N
b11 1
b11 7
b11 C
b11 4
b1011 Q
b11 &
b11 9
b11 O
b1000 R
b100000001011 H
b1000000010110010011 #
b1000000010110010011 K
b1000000 "
b1000000 J
b1000000 M
1!
#160
0!
#165
1(
bx +
bx F
b1110100 3
b1110100 L
10
b1001000 N
b1110100 1
b1110100 7
b1110100 C
b110000 5
b10 '
b10 ?
b110 )
b110 @
b110 G
b11000 .
b11000 :
b11000 A
b1000100 4
b110000 *
b110000 I
b1101111 >
b1 Q
b0 &
b0 9
b0 O
b0 R
bx %
bx 8
bx E
bx P
b10000 S
b1100000000000000001 H
b1 =
b11000000000000000011101111 #
b11000000000000000011101111 K
b1000100 "
b1000100 J
b1000100 M
1!
#170
0!
#175
0(
b1111000 3
b1111000 L
00
b11111111111111111111111111110000 5
b0 '
b0 ?
b0 )
b0 @
b0 G
b0 .
b0 :
b0 A
b11111111111111111111111111110000 *
b11111111111111111111111111110000 I
b11011011 1
b11011011 7
b11011011 C
b11011011 N
b10011 >
b10 Q
b11101011 &
b11101011 9
b11101011 O
b10 R
b1111111100000001000000010 H
b1111111 =
b11101011 4
b11111111000000010000000100010011 #
b11111111000000010000000100010011 K
b1110100 "
b1110100 J
b1110100 M
1!
#180
0!
#185
b0xxxxxxxxxxxxxxxxxxxxxxxx +
b0xxxxxxxxxxxxxxxxxxxxxxxx F
b1111100 3
b1111100 L
b1 '
b1 ?
b0 5
b0xxxxxxxxxxxxxxxxxxxxxxxx N
0$
1,
b1 )
b1 @
b1 G
b0 2
b0 6
b0 B
b0 *
b0 I
b11011011 1
b11011011 7
b11011011 C
b100011 >
b0 Q
b10 -
b10 ;
b10 D
b10 .
b10 :
b10 A
b10 <
b11 %
b11 8
b11 E
b11 P
b1000 S
b10000001001000000 H
b0 =
b11011011 4
b100000010010000000100011 #
b100000010010000000100011 K
b1111000 "
b1111000 J
b1111000 M
b11011011 &
b11011011 9
b11011011 O
1!
#190
0!
#195
bx N
bx +
bx F
b10000000 3
b10000000 L
b11011111 1
b11011111 7
b11011111 C
b100 5
b100 *
b100 I
b100 Q
b1001 S
b10010001001000100 H
b100100010010001000100011 #
b100100010010001000100011 K
b1111100 "
b1111100 J
b1111100 M
1!
#200
0!
#205
b11 N
b11 +
b11 F
b10000100 3
b10000100 L
b11100011 1
b11100011 7
b11100011 C
b1000 5
b1000 *
b1000 I
b1000 Q
b0 %
b0 8
b0 E
b0 P
b10010 S
b100100001001001000 H
b1001000010010010000100011 #
b1001000010010010000100011 K
b10000000 "
b10000000 J
b10000000 M
1!
#210
0!
#215
b0 N
b0 +
b0 F
b10001000 3
b10001000 L
b11100111 1
b11100111 7
b11100111 C
b1100 5
b1100 *
b1100 I
b1100 Q
b1 %
b1 8
b1 E
b1 P
b10011 S
b100110001001001100 H
b1001100010010011000100011 #
b1001100010010011000100011 K
b10000100 "
b10000100 J
b10000100 M
1!
#220
0!
#225
b1 +
b1 F
b10001100 3
b10001100 L
b1 N
b0 '
b0 ?
b1 1
b1 7
b1 C
b0 5
1$
0,
b0 )
b0 @
b0 G
b1 4
b0 *
b0 I
b10011 >
b1000 Q
b0 -
b0 ;
b0 D
b0 .
b0 :
b0 A
b0 <
b1 &
b1 9
b1 O
b1010 R
b0 %
b0 8
b0 E
b0 P
b0 S
b101000001000 H
b1010000010000010011 #
b1010000010000010011 K
b10001000 "
b10001000 J
b10001000 M
1!
#230
0!
#235
b0 +
b0 F
b10010000 3
b10010000 L
b11 N
b11 1
b11 7
b11 C
b11 4
b1001 Q
b11 &
b11 9
b11 O
b1011 R
b101100001001 H
b1011000010010010011 #
b1011000010010010011 K
b10001100 "
b10001100 J
b10001100 M
1!
#240
0!
#245
bx +
bx F
b10010100 3
b10010100 L
b0 N
b0 1
b0 7
b0 C
b0 4
b10010 Q
b0 &
b0 9
b0 O
b0 R
b10010 H
b100100010011 #
b100100010011 K
b10010000 "
b10010000 J
b10010000 M
1!
#250
0!
#255
b10011000 3
b10011000 L
b10011 Q
b10011 H
b100110010011 #
b100110010011 K
b10010100 "
b10010100 J
b10010100 M
1!
#260
0!
#265
b0xxxxxxxxxxxxxxxx +
b0xxxxxxxxxxxxxxxx F
b10011100 3
b10011100 L
b10011000 4
b10101000 1
b10101000 7
b10101000 C
10
b10011100 N
b10000 5
0$
b10 '
b10 ?
b101 )
b101 @
b101 G
b0 2
b0 6
b0 B
b10000 *
b10000 I
b1100011 >
b10000 Q
b101 -
b101 ;
b101 D
b1101 .
b1101 :
b1101 A
b101 <
b11 %
b11 8
b11 E
b11 P
b1001 S
b10010 R
b10011001010110000 H
b100110010101100001100011 #
b100110010101100001100011 K
b10011000 "
b10011000 J
b10011000 M
1!
#270
0!
#275
b0 +
b0 F
b10100000 3
b10100000 L
00
b1 5
1$
b0 '
b0 ?
b0 )
b0 @
b0 G
b1000 *
b1000 I
b1 1
b1 7
b1 C
b1 N
0/
b110011 >
b10011 Q
b10011 R
b0 -
b0 ;
b0 D
b0 .
b0 :
b0 A
b0 <
b1 %
b1 8
b1 E
b1 P
b1000 S
b10001001100010011 H
b0 4
b100010011000100110110011 #
b100010011000100110110011 K
b10011100 "
b10011100 J
b10011100 M
1!
#280
0!
#285
b0 +
b0 F
b10100100 3
b10100100 L
b1 N
b1 *
b1 I
b1 1
b1 7
b1 C
b10010 Q
1/
b10011 >
b10010 R
b1001000 %
b1001000 8
b1001000 E
b1001000 P
b1 S
b11001000010010 H
b0 4
b110010000100100010011 #
b110010000100100010011 K
b10100000 "
b10100000 J
b10100000 M
b0 &
b0 9
b0 O
1!
#290
0!
#295
bx +
bx F
1(
b10011000 3
b10011000 L
b10100100 4
b10011000 1
b10011000 7
b10011000 C
10
b10101000 N
b11111111111111111111111111110100 5
0$
b10 '
b10 ?
b101 )
b101 @
b101 G
b1000 .
b1000 :
b1000 A
b11111111111111111111111111110100 *
b11111111111111111111111111110100 I
b1100011 >
b10101 Q
b0 %
b0 8
b0 E
b0 P
b0 S
b0 R
b1111111000000000000010101 H
b1111111 =
b0 &
b0 9
b0 O
b11111110000000000000101011100011 #
b11111110000000000000101011100011 K
b10100100 "
b10100100 J
b10100100 M
1!
#300
0!
#305
b10011100 3
b10011100 L
b0xxxxxxxxxxxxxxxx +
b0xxxxxxxxxxxxxxxx F
0(
b10000 5
b10000 *
b10000 I
b10101000 1
b10101000 7
b10101000 C
b10011100 N
b10000 Q
b101 -
b101 ;
b101 D
b1101 .
b1101 :
b1101 A
b101 <
b11 %
b11 8
b11 E
b11 P
b1001 S
b1 &
b1 9
b1 O
b10010 R
b10011001010110000 H
b0 =
b10011000 4
b100110010101100001100011 #
b100110010101100001100011 K
b10011000 "
b10011000 J
b10011000 M
1!
#310
0!
#315
0(
bx +
bx F
b10100000 3
b10100000 L
00
b1 5
1$
b0 '
b0 ?
b0 )
b0 @
b0 G
b1000 *
b1000 I
b10 1
b10 7
b10 C
b10 N
0/
b110011 >
b10011 Q
b10011 R
b0 -
b0 ;
b0 D
b0 .
b0 :
b0 A
b0 <
b1 %
b1 8
b1 E
b1 P
b1000 S
b10001001100010011 H
b1 4
b100010011000100110110011 #
b100010011000100110110011 K
b10011100 "
b10011100 J
b10011100 M
1!
#320
0!
#325
bx +
bx F
b10100100 3
b10100100 L
b10 N
b1 *
b1 I
b10 1
b10 7
b10 C
b10010 Q
1/
b10011 >
b10010 R
b1001000 %
b1001000 8
b1001000 E
b1001000 P
b1 S
b11001000010010 H
b1 4
b110010000100100010011 #
b110010000100100010011 K
b10100000 "
b10100000 J
b10100000 M
b1 &
b1 9
b1 O
1!
#330
0!
#335
bx +
bx F
1(
b10011000 3
b10011000 L
10
b10101000 N
b11111111111111111111111111110100 5
b10011000 1
b10011000 7
b10011000 C
0$
b10 '
b10 ?
b101 )
b101 @
b101 G
b1000 .
b1000 :
b1000 A
b11111111111111111111111111110100 *
b11111111111111111111111111110100 I
b10100100 4
b1100011 >
b10101 Q
b0 %
b0 8
b0 E
b0 P
b0 S
b0 R
b1111111000000000000010101 H
b1111111 =
b0 &
b0 9
b0 O
b11111110000000000000101011100011 #
b11111110000000000000101011100011 K
b10100100 "
b10100100 J
b10100100 M
1!
#340
0!
#345
b10011100 3
b10011100 L
b0xxxxxxxxxxxxxxxx +
b0xxxxxxxxxxxxxxxx F
0(
b10000 5
b10000 *
b10000 I
b10101000 1
b10101000 7
b10101000 C
b10011100 N
b10000 Q
b101 -
b101 ;
b101 D
b1101 .
b1101 :
b1101 A
b101 <
b11 %
b11 8
b11 E
b11 P
b1001 S
b10 &
b10 9
b10 O
b10010 R
b10011001010110000 H
b0 =
b10011000 4
b100110010101100001100011 #
b100110010101100001100011 K
b10011000 "
b10011000 J
b10011000 M
1!
#350
0!
#355
b0 +
b0 F
b10100000 3
b10100000 L
00
b1 5
1$
b0 '
b0 ?
b0 )
b0 @
b0 G
b1000 *
b1000 I
b11 1
b11 7
b11 C
b11 N
0/
b110011 >
b10011 Q
b10011 R
b0 -
b0 ;
b0 D
b0 .
b0 :
b0 A
b0 <
b1 %
b1 8
b1 E
b1 P
b1000 S
b10001001100010011 H
b10 4
b100010011000100110110011 #
b100010011000100110110011 K
b10011100 "
b10011100 J
b10011100 M
1!
#360
0!
#365
b0 +
b0 F
b10100100 3
b10100100 L
b11 N
b1 *
b1 I
b11 1
b11 7
b11 C
b10010 Q
1/
b10011 >
b10010 R
b1001000 %
b1001000 8
b1001000 E
b1001000 P
b1 S
b11001000010010 H
b10 4
b110010000100100010011 #
b110010000100100010011 K
b10100000 "
b10100000 J
b10100000 M
b10 &
b10 9
b10 O
1!
#370
0!
#375
bx +
bx F
1(
b10011000 3
b10011000 L
10
b10101000 N
b11111111111111111111111111110100 5
b10011000 1
b10011000 7
b10011000 C
0$
b10 '
b10 ?
b101 )
b101 @
b101 G
b1000 .
b1000 :
b1000 A
b11111111111111111111111111110100 *
b11111111111111111111111111110100 I
b10100100 4
b1100011 >
b10101 Q
b0 %
b0 8
b0 E
b0 P
b0 S
b0 R
b1111111000000000000010101 H
b1111111 =
b0 &
b0 9
b0 O
b11111110000000000000101011100011 #
b11111110000000000000101011100011 K
b10100100 "
b10100100 J
b10100100 M
1!
#380
0!
#385
b10101000 3
b10101000 L
b0xxxxxxxxxxxxxxxx +
b0xxxxxxxxxxxxxxxx F
b10000 5
b10000 *
b10000 I
b10101000 1
b10101000 7
b10101000 C
b10011100 N
b10000 Q
b101 -
b101 ;
b101 D
b1101 .
b1101 :
b1101 A
b101 <
b11 %
b11 8
b11 E
b11 P
b1001 S
b11 &
b11 9
b11 O
b10010 R
b10011001010110000 H
b0 =
b10011000 4
b100110010101100001100011 #
b100110010101100001100011 K
b10011000 "
b10011000 J
b10011000 M
1!
#390
0!
