Mono_CPU/Instruction_Memory/instruction_memory.v
module instruction_memory(
    input logic [31:0] program_counter,
    output logic [31:0] instruction
    );
    logic [7:0] memory [0:512];
    initial begin
        $readmemh("mul.mem", memory);
    end
    assign instruction = {
        memory[program_counter],
        memory[program_counter+1],
        memory[program_counter+2],
        memory[program_counter+3]};

endmodule

Mono_CPU/Instruction_Memory/instruction_memory_tb.v
module instruction_memory_tb;

  logic [31:0] program_counter;
  logic [31:0] instruction;

  instruction_memory dut (
    .program_counter(program_counter),
    .instruction(instruction)
  );

  initial begin
    $dumpfile("dump.vcd"); 
    $dumpvars(0, instruction_memory_tb);
    // Initialize program_counter
    program_counter = 0;
    
    // Wait for some time for memory initialization
    #100;

    // Read and display the first 10 instructions
    for (int i = 0; i < 22; i = i + 1) begin
      #10; // Advance simulation time
      program_counter = program_counter + 4;
    end
    
    // End of simulation
    $finish;
  end

endmodule

Mono_CPU/Instruction_Memory/dump.vcd
$date
	Fri Apr 19 14:10:01 2024
$end
$version
	Icarus Verilog
$end
$timescale
	1s
$end
$scope module instruction_memory_tb $end
$var wire 32 ! instruction [31:0] $end
$var reg 32 " program_counter [31:0] $end
$scope module dut $end
$var wire 32 # program_counter [31:0] $end
$var wire 32 $ instruction [31:0] $end
$upscope $end
$scope begin $ivl_for_loop0 $end
$var integer 32 % i [31:0] $end
$upscope $end
$upscope $end
$enddefinitions $end
$comment Show the parameter values. $end
$dumpall
$end
#0
$dumpvars
b0 %
b111000000000010100010011 $
b0 #
b0 "
b111000000000010100010011 !
$end
#110
b1 %
b11100000000010110010011 !
b11100000000010110010011 $
b100 "
b100 #
#120
b10 %
b100000000000000011101111 !
b100000000000000011101111 $
b1000 "
b1000 #
#130
b11 %
b100000000000000010001100011 !
b100000000000000010001100011 $
b1100 "
b1100 #
#140
b100 %
b11111111010000010000000100010011 !
b11111111010000010000000100010011 $
b10000 "
b10000 #
#150
b101 %
b100000010010000000100011 !
b100000010010000000100011 $
b10100 "
b10100 #
#160
b110 %
b100100010010001000100011 !
b100100010010001000100011 $
b11000 "
b11000 #
#170
b111 %
b1001000010010010000100011 !
b1001000010010010000100011 $
b11100 "
b11100 #
#180
b1000 %
b1010000010000010011 !
b1010000010000010011 $
b100000 "
b100000 #
#190
b1001 %
b1011000010010010011 !
b1011000010010010011 $
b100100 "
b100100 #
#200
b1010 %
b100100010011 !
b100100010011 $
b101000 "
b101000 #
#210
b1011 %
b100101000100100001100011 !
b100101000100100001100011 $
b101100 "
b101100 #
#220
b1100 %
b1000000100101000000010000110011 !
b1000000100101000000010000110011 $
b110000 "
b110000 #
#230
b1101 %
b110010000100100010011 !
b110010000100100010011 $
b110100 "
b110100 #
#240
b1110 %
b11111110000000000000101011100011 !
b11111110000000000000101011100011 $
b111000 "
b111000 #
#250
b1111 %
b10010000010100010011 !
b10010000010100010011 $
b111100 "
b111100 #
#260
b10000 %
b10010010000000011 !
b10010010000000011 $
b1000000 "
b1000000 #
#270
b10001 %
b10000010010010010000011 !
b10000010010010010000011 $
b1000100 "
b1000100 #
#280
b10010 %
b100000010010100100000011 !
b100000010010100100000011 $
b1001000 "
b1001000 #
#290
b10011 %
b110000010000000100010011 !
b110000010000000100010011 $
b1001100 "
b1001100 #
#300
b10100 %
b1000000011100111 !
b1000000011100111 $
b1010000 "
b1010000 #
#310
b10101 %
b10011 !
b10011 $
b1010100 "
b1010100 #
#320
b10110 %
bx !
bx $
b1011000 "
b1011000 #
