Mono_CPU/PC/program_counter.v
module program_counter(
    input clk, 
    input logic [31:0] pc_input, 
    output logic [31:0] pc_output
    );
    
    always @ (posedge clk)
        pc_output <= pc_input;

endmodule

Mono_CPU/PC/program_counter_tb.v
module program_counter_tb;

  logic [31:0] pc_input, pc_output;
  logic clk;

  program_counter dut(
    .clk(clk),
    .pc_input(pc_input),
    .pc_output(pc_output)
  );


  initial begin
    clk = 0;
    forever #5 clk = ~clk;
  end

  initial begin
    $dumpfile("dump.vcd");
    $dumpvars(0,program_counter_tb);

    pc_input = 32'h00000000;
    #10 //0

    pc_input = 32'h00000001;
    #10 //10

    pc_input = 32'h00000002;
    #10 //20
    pc_input = 32'h00000003;
    #10 //30
    pc_input = 32'h00000004;
    #10 //40

  
    $finish;
  end





endmodule

Mono_CPU/PC/dump.vcd
$date
	Sat Apr 20 19:17:34 2024
$end
$version
	Icarus Verilog
$end
$timescale
	1s
$end
$scope module program_counter_tb $end
$var wire 32 ! pc_output [31:0] $end
$var reg 1 " clk $end
$var reg 32 # pc_input [31:0] $end
$scope module dut $end
$var wire 1 " clk $end
$var wire 32 $ pc_input [31:0] $end
$var reg 32 % pc_output [31:0] $end
$upscope $end
$upscope $end
$enddefinitions $end
$comment Show the parameter values. $end
$dumpall
$end
#0
$dumpvars
bx %
b0 $
b0 #
0"
bx !
$end
#5
b0 !
b0 %
1"
#10
0"
b1 #
b1 $
#15
b1 !
b1 %
1"
#20
0"
b10 #
b10 $
#25
b10 !
b10 %
1"
#30
0"
b11 #
b11 $
#35
b11 !
b11 %
1"
#40
0"
b100 #
b100 $
#45
b100 !
b100 %
1"
